odoo/addons/mail_improved_tracking_value/README.rst
odoo/addons/mail_improved_tracking_value/__init__.py
odoo/addons/mail_improved_tracking_value/__manifest__.py
odoo/addons/mail_improved_tracking_value/i18n/es.po
odoo/addons/mail_improved_tracking_value/i18n/it.po
odoo/addons/mail_improved_tracking_value/i18n/mail_improved_tracking_value.pot
odoo/addons/mail_improved_tracking_value/models/__init__.py
odoo/addons/mail_improved_tracking_value/models/mail_message.py
odoo/addons/mail_improved_tracking_value/models/mail_tracking_value.py
odoo/addons/mail_improved_tracking_value/static/description/icon.png
odoo/addons/mail_improved_tracking_value/tests/__init__.py
odoo/addons/mail_improved_tracking_value/tests/test_improved_tracking_value.py
odoo/addons/mail_improved_tracking_value/views/mail_tracking_value.xml
odoo_addon_mail_improved_tracking_value-16.0.1.0.0.6.dist-info/METADATA
odoo_addon_mail_improved_tracking_value-16.0.1.0.0.6.dist-info/WHEEL
odoo_addon_mail_improved_tracking_value-16.0.1.0.0.6.dist-info/top_level.txt
odoo_addon_mail_improved_tracking_value-16.0.1.0.0.6.dist-info/RECORD
